README.md
setup.py
holiday_oracle.egg-info/PKG-INFO
holiday_oracle.egg-info/SOURCES.txt
holiday_oracle.egg-info/dependency_links.txt
holiday_oracle.egg-info/requires.txt
holiday_oracle.egg-info/top_level.txt
offchain/__init__.py
offchain/api.py