Metadata-Version: 2.1
Name: holiday-oracle
Version: 0.1.1
Summary: Provides access to global holidays via the Off Chain Data API.
Home-page: https://github.com/OffChainData/holiday-oracle-python
Author: Off Chain Data
Author-email: hello@offchaindata.com
License: UNKNOWN
Platform: UNKNOWN
Classifier: Programming Language :: Python :: 3
Classifier: License :: OSI Approved :: MIT License
Classifier: Operating System :: OS Independent
